setup.py
object_pool/__init__.py
object_pool.egg-info/PKG-INFO
object_pool.egg-info/SOURCES.txt
object_pool.egg-info/dependency_links.txt
object_pool.egg-info/top_level.txt
object_pool/test/__init__.py
object_pool/test/test_object_pool.py