Metadata-Version: 1.0
Name: object-pool
Version: 0.2
Summary: thread-safe python object pool
Home-page: https://github.com/btmorex/object_pool
Author: Avery Fay
Author-email: avery@shadypixel.com
License: MIT
Platform: UNKNOWN
